holo_rec.py
holo_rec_jw-0.1.dist-info/METADATA
holo_rec_jw-0.1.dist-info/WHEEL
holo_rec_jw-0.1.dist-info/top_level.txt
holo_rec_jw-0.1.dist-info/RECORD
