Metadata-Version: 2.1
Name: holo-rec-jw
Version: 0.1
Summary: jiwon
Home-page: UNKNOWN
Author: jiwon
Author-email: jwkang@kw.ac.kr
License: UNKNOWN
Platform: UNKNOWN
Requires-Dist: numpy (==1.18.1)
